{
  "nav": {
    "experience": "الخبرة",
    "education": "التعليم",
    "contact": "اتصل بي"
  },
  "intro": {
    "title": "مطور فرونت إند & مصمم UX/UI",
    "location": "مقيم في ساو باولو 📍"
  },
  "experience": {
    "sectionTitle": "الخبرة",
    "text": "أطور مشاريع تركز على <strong>الواجهة الخلفية</strong> و<strong>واجهات برمجة التطبيقات</strong> باستخدام <strong>TypeScript</strong>، مع إعطاء الأولوية لكود نظيف وقابل للتوسع. بالإضافة إلى بناء خدمات <strong>قوية</strong>، لدي خبرة في <strong>الواجهة الأمامية</strong> مع <strong>JavaScript</strong> و<strong>APIs</strong> خارجية، كما في مشروع Animais Fantásticos، وفي تصميم الواجهات <strong>(UX/UI Design)</strong>، المطبق في مشروع Bikcraft.",
    "projects": [
      {
        "year": "2023",
        "name": "Bikcraft",
        "technologies": "التقنيات",
        "description": "دراجات كهربائية عالية الدقة والجودة، مصممة خصيصًا للعميل. استكشف العالم بسرعة تناسبك مع Bikcraft.",
        "skills": ["HTML", "CSS", "JAVASCRIPT", "تصميم UX", "تصميم UI"]
      },
      {
        "year": "2023",
        "name": "الحيوانات الرائعة",
        "technologies": "التقنيات",
        "description": "الثعالب هي حيوانات ثديية وكلية الغذاء تنتمي إلى عائلة الكلبيات. هي ثعالب متوسطة الحجم.",
        "skills": ["HTML", "CSS", "JAVASCRIPT", "APIS", "تصميم UX", "تصميم UI"]
      },
      {
        "year": "2024",
        "name": "المكعب",
        "technologies": "التقنيات",
        "description": "كن مبدعًا، طور مهاراتك الحركية، التركيز، الصبر وساعد عقلك على تحسين قدراته الإدراكية. اشترِ مكعبك السحري.",
        "skills": [
          "HTML",
          "CSS",
          "JAVASCRIPT",
          "APIS",
          "تصميم UX",
          "مدير العلامات من جوجل (Google Tag Manager)"
        ]
      }
    ]
  },
  "education": {
    "sectionTitle": "التعليم",
    "text": "طالب في تخصص <strong>هندسة البرمجيات</strong> (Unimar) مع مؤهل تقني في <strong>تطوير الأنظمة</strong> من Etec Professor Basilides de Godoy. أبحث عن أول فرصة لي في مجال التكنولوجيا، مع التركيز على <strong>تطوير الواجهة الخلفية.</strong>",
    "schools": [
      {
        "type": "فني",
        "course": "تطوير الأنظمة",
        "institution": "ETEC Basilides de Godoy"
      },
      {
        "type": "لقب متميز 🏆",
        "course": "أفضل محلل ومطور تطبيقات الجوال",
        "institution": "ETEC Basilides de Godoy"
      },
      {
        "type": "الشهادات",
        "course": "فرونت إند & تصميم UX/UI",
        "institution": "ORIGAMID"
      }
    ],
    "extra": {
      "intensiveCoursesTitle": "دورات مكثفة",
      "courses": [
        "تصميم UX & تصميم UI <span>34 ساعة</span>",
        "فرونت إند للمبتدئين <span>46 ساعة</span>"
      ]
    }
  },
  "footer": {
    "text": "أنا متاح للمشاريع الجديدة حاليًا. اتصل بي لنرتب محادثة 👋",
    "email": "cristiaguedes1402@gmail.com",
    "phone": "+55 11 93055-3294",
    "copy": "devcris."
  }
}
